hotspot/__init__.py
hotspot/bernoulli_model.py
hotspot/danb_model.py
hotspot/hotspot.py
hotspot/knn.py
hotspot/local_stats.py
hotspot/local_stats_pairs.py
hotspot/modules.py
hotspot/none_model.py
hotspot/normal_model.py
hotspot/plots.py
hotspot/sim_data.py
hotspot/utils.py
hotspotsc-1.1.3.dist-info/LICENSE
hotspotsc-1.1.3.dist-info/METADATA
hotspotsc-1.1.3.dist-info/WHEEL
hotspotsc-1.1.3.dist-info/RECORD
