Metadata-Version: 2.3
Name: hotspotsc
Version: 1.1.3
Summary: Identifying informative genes (and gene modules) in a single-cell dataset.
License: MIT
Author: David DeTomaso
Author-email: David.DeTomaso@berkeley.edu
Requires-Python: >=3.7,<4.0
Classifier: Development Status :: 4 - Beta
Classifier: Intended Audience :: Science/Research
Classifier: License :: OSI Approved :: MIT License
Classifier: Natural Language :: English
Classifier: Operating System :: MacOS :: MacOS X
Classifier: Operating System :: Microsoft :: Windows
Classifier: Operating System :: POSIX :: Linux
Classifier: Programming Language :: Python :: 3
Classifier: Programming Language :: Python :: 3.7
Classifier: Programming Language :: Python :: 3.8
Classifier: Programming Language :: Python :: 3.9
Classifier: Programming Language :: Python :: 3.10
Classifier: Programming Language :: Python :: 3.11
Classifier: Programming Language :: Python :: 3.12
Classifier: Programming Language :: Python :: 3.13
Classifier: Topic :: Scientific/Engineering :: Bio-Informatics
Provides-Extra: docs
Provides-Extra: test
Requires-Dist: anndata (>=0.7)
Requires-Dist: importlib-metadata (>1.0) ; python_version < "3.8"
Requires-Dist: ipython ; extra == "docs"
Requires-Dist: matplotlib (>=3.0.0)
Requires-Dist: myst-nb ; extra == "docs"
Requires-Dist: numba (>=0.43.1)
Requires-Dist: numpy (>=1.16.4)
Requires-Dist: pandas (>=0.24.0)
Requires-Dist: pynndescent (>=0.5)
Requires-Dist: pytest (>=5.0) ; extra == "test"
Requires-Dist: scanpy ; extra == "test"
Requires-Dist: scikit-learn (>=0.21.2)
Requires-Dist: scipy (>=1.2.1)
Requires-Dist: seaborn (>=0.9.0)
Requires-Dist: sphinx (>=4.1) ; extra == "docs"
Requires-Dist: sphinx-book-theme (>=0.2.0) ; extra == "docs"
Requires-Dist: statsmodels (>=0.9.0)
Requires-Dist: tqdm (>=4.32.2)
Project-URL: Documentation, https://hotspot.readthedocs.io/
Project-URL: Homepage, https://github.com/yoseflab/hostpost
